{
  "dataset_info": {
    "seed": 136,
    "dataset_index": 5,
    "node_count": 20,
    "edge_count": 20,
    "graph_type": "SF",
    "shifted_nodes": [
      14,
      17,
      4,
      12
    ],
    "shift_types": {
      "14": [
        "sin_cos"
      ],
      "17": [
        "sin_cos"
      ],
      "4": [
        "noise_N02"
      ],
      "12": [
        "noise_N02"
      ]
    },
    "shift_case": "sin_cos_noise_N02",
    "deleted_parents": {}
  },
  "model": "linearccp",
  "exp_type": "synthetic",
  "config_name": "SF",
  "device": "cuda:0",
  "linearccp": {
    "shifted_nodes": [
      4,
      8,
      12,
      14,
      16,
      17
    ],
    "functional_change_nodes": [
      8,
      14
    ],
    "noise_change_nodes": [
      4,
      8,
      12,
      14,
      16,
      17
    ],
    "node_results": {
      "1": {
        "is_shifted": false,
        "parents": [
          0
        ],
        "function_test": {
          "f_statistic": 1.5778869825827844,
          "p_value": 0.20906825398230122,
          "is_function_changed": false,
          "beta_env1": [
            0.0005124661919973929
          ],
          "beta_env2": [
            -0.00496259884276858
          ]
        },
        "noise_test": {
          "ks_statistic": 0.0041799999999999615,
          "p_value": 0.7732497377117262,
          "is_noise_changed": false
        }
      },
      "2": {
        "is_shifted": false,
        "parents": [
          1
        ],
        "function_test": {
          "f_statistic": 0.07861103679271657,
          "p_value": 0.7791891692845458,
          "is_function_changed": false,
          "beta_env1": [
            0.14288783848308623
          ],
          "beta_env2": [
            0.1411094514272716
          ]
        },
        "noise_test": {
          "ks_statistic": 0.006299999999999972,
          "p_value": 0.2730447345623205,
          "is_noise_changed": false
        }
      },
      "3": {
        "is_shifted": false,
        "parents": [
          1
        ],
        "function_test": {
          "f_statistic": 0.7444547206888811,
          "p_value": 0.38823966765009443,
          "is_function_changed": false,
          "beta_env1": [
            0.14010747667934387
          ],
          "beta_env2": [
            0.14557499599204035
          ]
        },
        "noise_test": {
          "ks_statistic": 0.003180000000000016,
          "p_value": 0.9614285356614354,
          "is_noise_changed": false
        }
      },
      "4": {
        "is_shifted": true,
        "parents": [
          1
        ],
        "function_test": {
          "f_statistic": 0.9962050891906952,
          "p_value": 0.31823292602163167,
          "is_function_changed": false,
          "beta_env1": [
            0.14089409409204598
          ],
          "beta_env2": [
            0.1482985008792244
          ]
        },
        "noise_test": {
          "ks_statistic": 0.06918000000000002,
          "p_value": 1.7668038477700894e-104,
          "is_noise_changed": true
        }
      },
      "5": {
        "is_shifted": false,
        "parents": [
          3
        ],
        "function_test": {
          "f_statistic": 0.1729610230112337,
          "p_value": 0.6774944418249649,
          "is_function_changed": false,
          "beta_env1": [
            0.1193861391895382
          ],
          "beta_env2": [
            0.11678371648938672
          ]
        },
        "noise_test": {
          "ks_statistic": 0.0037800000000000056,
          "p_value": 0.8659726587393721,
          "is_noise_changed": false
        }
      },
      "6": {
        "is_shifted": false,
        "parents": [
          1
        ],
        "function_test": {
          "f_statistic": 0.4861438142249746,
          "p_value": 0.48565414280358055,
          "is_function_changed": false,
          "beta_env1": [
            0.13989050564877858
          ],
          "beta_env2": [
            0.14428747272241607
          ]
        },
        "noise_test": {
          "ks_statistic": 0.0033199999999999896,
          "p_value": 0.9448560509635644,
          "is_noise_changed": false
        }
      },
      "7": {
        "is_shifted": false,
        "parents": [
          1
        ],
        "function_test": {
          "f_statistic": 0.0024518979353486316,
          "p_value": 0.9605076731566189,
          "is_function_changed": false,
          "beta_env1": [
            0.1397531592578423
          ],
          "beta_env2": [
            0.13943949717360007
          ]
        },
        "noise_test": {
          "ks_statistic": 0.0025199999999999667,
          "p_value": 0.9972431501273936,
          "is_noise_changed": false
        }
      },
      "8": {
        "is_shifted": true,
        "parents": [
          4
        ],
        "function_test": {
          "f_statistic": 483.0140356870917,
          "p_value": 1.1102230246251565e-16,
          "is_function_changed": true,
          "beta_env1": [
            0.11923748174184247
          ],
          "beta_env2": [
            -0.0064638043133626345
          ]
        },
        "noise_test": {
          "ks_statistic": 0.013660000000000005,
          "p_value": 0.00017582103023244282,
          "is_noise_changed": true
        }
      },
      "9": {
        "is_shifted": false,
        "parents": [
          0
        ],
        "function_test": {
          "f_statistic": 0.03929186717192389,
          "p_value": 0.8428719641500353,
          "is_function_changed": false,
          "beta_env1": [
            0.001920422720080515
          ],
          "beta_env2": [
            0.002785283750973107
          ]
        },
        "noise_test": {
          "ks_statistic": 0.0046399999999999775,
          "p_value": 0.6529601030662224,
          "is_noise_changed": false
        }
      },
      "10": {
        "is_shifted": false,
        "parents": [
          9
        ],
        "function_test": {
          "f_statistic": 0.3175357469599551,
          "p_value": 0.5730936113665512,
          "is_function_changed": false,
          "beta_env1": [
            0.14021134423236867
          ],
          "beta_env2": [
            0.14378154426598969
          ]
        },
        "noise_test": {
          "ks_statistic": 0.002380000000000021,
          "p_value": 0.998852519535543,
          "is_noise_changed": false
        }
      },
      "11": {
        "is_shifted": false,
        "parents": [
          6
        ],
        "function_test": {
          "f_statistic": 0.9561400168723513,
          "p_value": 0.3281636831387469,
          "is_function_changed": false,
          "beta_env1": [
            0.11792429280736716
          ],
          "beta_env2": [
            0.12405937565994546
          ]
        },
        "noise_test": {
          "ks_statistic": 0.0027600000000000957,
          "p_value": 0.9909175199001018,
          "is_noise_changed": false
        }
      },
      "12": {
        "is_shifted": true,
        "parents": [
          0
        ],
        "function_test": {
          "f_statistic": 1.2548642021979612,
          "p_value": 0.2626281609546611,
          "is_function_changed": false,
          "beta_env1": [
            -0.00504187188107811
          ],
          "beta_env2": [
            0.0005483021026714789
          ]
        },
        "noise_test": {
          "ks_statistic": 0.05521999999999999,
          "p_value": 1.064359416497652e-66,
          "is_noise_changed": true
        }
      },
      "13": {
        "is_shifted": false,
        "parents": [
          1
        ],
        "function_test": {
          "f_statistic": 1.3281513911402854,
          "p_value": 0.2491371086374805,
          "is_function_changed": false,
          "beta_env1": [
            0.14367857460080286
          ],
          "beta_env2": [
            0.1509857051659796
          ]
        },
        "noise_test": {
          "ks_statistic": 0.0038600000000000023,
          "p_value": 0.8488795355638253,
          "is_noise_changed": false
        }
      },
      "14": {
        "is_shifted": true,
        "parents": [
          13
        ],
        "function_test": {
          "f_statistic": 141.6045603508838,
          "p_value": 1.1102230246251565e-16,
          "is_function_changed": true,
          "beta_env1": [
            0.10558907592424423
          ],
          "beta_env2": [
            0.18371294446429023
          ]
        },
        "noise_test": {
          "ks_statistic": 0.052180000000000004,
          "p_value": 1.339038704619305e-59,
          "is_noise_changed": true
        }
      },
      "15": {
        "is_shifted": false,
        "parents": [
          10
        ],
        "function_test": {
          "f_statistic": 0.01413216110286717,
          "p_value": 0.9053716431973421,
          "is_function_changed": false,
          "beta_env1": [
            0.10973729789630016
          ],
          "beta_env2": [
            0.1104797455799244
          ]
        },
        "noise_test": {
          "ks_statistic": 0.0055400000000001,
          "p_value": 0.4252530882663589,
          "is_noise_changed": false
        }
      },
      "16": {
        "is_shifted": true,
        "parents": [
          8
        ],
        "function_test": {
          "f_statistic": 0.17583135240381312,
          "p_value": 0.6749813615042322,
          "is_function_changed": false,
          "beta_env1": [
            0.11110324993091192
          ],
          "beta_env2": [
            0.10854934561706148
          ]
        },
        "noise_test": {
          "ks_statistic": 0.012239999999999918,
          "p_value": 0.0011070283735672873,
          "is_noise_changed": true
        }
      },
      "17": {
        "is_shifted": true,
        "parents": [
          4
        ],
        "function_test": {
          "f_statistic": 3.1138934419455344,
          "p_value": 0.07763024207668989,
          "is_function_changed": false,
          "beta_env1": [
            0.11978123934175375
          ],
          "beta_env2": [
            0.1305211893346187
          ]
        },
        "noise_test": {
          "ks_statistic": 0.07216,
          "p_value": 1.2020350775140287e-113,
          "is_noise_changed": true
        }
      },
      "18": {
        "is_shifted": false,
        "parents": [
          13
        ],
        "function_test": {
          "f_statistic": 1.939358626675899,
          "p_value": 0.163741286670135,
          "is_function_changed": false,
          "beta_env1": [
            0.11375717862882043
          ],
          "beta_env2": [
            0.10503158339709201
          ]
        },
        "noise_test": {
          "ks_statistic": 0.0040400000000000436,
          "p_value": 0.8075792965488091,
          "is_noise_changed": false
        }
      },
      "19": {
        "is_shifted": false,
        "parents": [
          13
        ],
        "function_test": {
          "f_statistic": 0.003102905065044072,
          "p_value": 0.9555779426629217,
          "is_function_changed": false,
          "beta_env1": [
            0.11616304507565146
          ],
          "beta_env2": [
            0.11581552884954192
          ]
        },
        "noise_test": {
          "ks_statistic": 0.004819999999999991,
          "p_value": 0.6050632197071624,
          "is_noise_changed": false
        }
      }
    },
    "metrics": {
      "true_positives": [
        4,
        12,
        14,
        17
      ],
      "false_positives": [
        8,
        16
      ],
      "false_negatives": [],
      "precision": 0.6666666666666666,
      "recall": 1.0,
      "f1_score": 0.8
    }
  },
  "complexity_analysis": {
    "success": true,
    "error": null,
    "dataset_params": {
      "n_samples": 50000,
      "n_nodes": 20,
      "avg_parents": 0.95,
      "max_parents": 1,
      "total_edges": 19
    },
    "time_complexity": {
      "execution_time_seconds": 1.210547924041748,
      "execution_time_minutes": 0.020175798734029134
    },
    "space_complexity": {
      "peak_rss_mb": 7380.93359375,
      "peak_memory_increase_mb": 0.0,
      "start_rss_mb": 7380.93359375,
      "os": "Linux"
    },
    "scalability_metrics": {
      "time_per_node_sec": 0.0605273962020874,
      "time_per_sample_sec": 2.421095848083496e-05,
      "time_per_edge_sec": 0.0637130486337762,
      "memory_per_node_mb": 0.0,
      "memory_per_sample_mb": 0.0
    }
  }
}