{
  "dataset_info": {
    "seed": 273,
    "dataset_index": 22,
    "node_count": 40,
    "edge_count": 40,
    "graph_type": "SF",
    "shifted_nodes": [
      15,
      19,
      21,
      28,
      31,
      14,
      22,
      25
    ],
    "shift_types": {
      "15": [
        "sin_cos"
      ],
      "19": [
        "sin_cos"
      ],
      "21": [
        "sin_cos"
      ],
      "28": [
        "sin_cos"
      ],
      "31": [
        "pa_delete"
      ],
      "14": [
        "pa_delete"
      ],
      "22": [
        "pa_delete"
      ],
      "25": [
        "pa_delete"
      ]
    },
    "shift_case": "sin_cos_pa_delete",
    "deleted_parents": {
      "31": 5,
      "14": 10,
      "22": 12,
      "25": 4
    }
  },
  "model": "linearccp",
  "exp_type": "synthetic",
  "config_name": "SF",
  "device": "cuda:0",
  "linearccp": {
    "shifted_nodes": [
      12,
      14,
      15,
      16,
      18,
      19,
      22,
      25,
      26,
      28,
      30,
      31
    ],
    "functional_change_nodes": [
      12,
      15,
      16,
      18,
      19,
      26,
      28,
      30,
      31
    ],
    "noise_change_nodes": [
      14,
      15,
      19,
      22,
      25,
      28,
      31
    ],
    "node_results": {
      "1": {
        "is_shifted": false,
        "parents": [
          0
        ],
        "function_test": {
          "f_statistic": 0.2848095254035479,
          "p_value": 0.5936254946978327,
          "is_function_changed": false,
          "beta_env1": [
            0.032663432092156205
          ],
          "beta_env2": [
            0.04965551536320151
          ]
        },
        "noise_test": {
          "ks_statistic": 0.039,
          "p_value": 0.43260886958153144,
          "is_noise_changed": false
        }
      },
      "2": {
        "is_shifted": false,
        "parents": [
          0
        ],
        "function_test": {
          "f_statistic": 2.851180962606061,
          "p_value": 0.09146304596184851,
          "is_function_changed": false,
          "beta_env1": [
            -0.03260088245991769
          ],
          "beta_env2": [
            0.019007274611120353
          ]
        },
        "noise_test": {
          "ks_statistic": 0.037,
          "p_value": 0.5005673707894058,
          "is_noise_changed": false
        }
      },
      "3": {
        "is_shifted": false,
        "parents": [
          1
        ],
        "function_test": {
          "f_statistic": 3.4431302583364696,
          "p_value": 0.06366256731482256,
          "is_function_changed": false,
          "beta_env1": [
            0.17126301227747825
          ],
          "beta_env2": [
            0.08923295425606284
          ]
        },
        "noise_test": {
          "ks_statistic": 0.048,
          "p_value": 0.19957365535779528,
          "is_noise_changed": false
        }
      },
      "4": {
        "is_shifted": false,
        "parents": [
          0
        ],
        "function_test": {
          "f_statistic": 0.1867981491976393,
          "p_value": 0.6656416448298368,
          "is_function_changed": false,
          "beta_env1": [
            0.00857918417591372
          ],
          "beta_env2": [
            -0.004650648460502598
          ]
        },
        "noise_test": {
          "ks_statistic": 0.037,
          "p_value": 0.5005673707894058,
          "is_noise_changed": false
        }
      },
      "5": {
        "is_shifted": false,
        "parents": [
          3
        ],
        "function_test": {
          "f_statistic": 0.3251361042511497,
          "p_value": 0.5686014367317767,
          "is_function_changed": false,
          "beta_env1": [
            0.1364409650384457
          ],
          "beta_env2": [
            0.1111639675384019
          ]
        },
        "noise_test": {
          "ks_statistic": 0.029,
          "p_value": 0.7946637387576738,
          "is_noise_changed": false
        }
      },
      "6": {
        "is_shifted": false,
        "parents": [
          3
        ],
        "function_test": {
          "f_statistic": 0.36310591752713545,
          "p_value": 0.5468547792325931,
          "is_function_changed": false,
          "beta_env1": [
            0.10698279191042352
          ],
          "beta_env2": [
            0.08025615987443288
          ]
        },
        "noise_test": {
          "ks_statistic": 0.025,
          "p_value": 0.9136894237272155,
          "is_noise_changed": false
        }
      },
      "7": {
        "is_shifted": false,
        "parents": [
          0
        ],
        "function_test": {
          "f_statistic": 0.19910350842260155,
          "p_value": 0.6554938436857376,
          "is_function_changed": false,
          "beta_env1": [
            -0.005449674298932758
          ],
          "beta_env2": [
            -0.019470012869328934
          ]
        },
        "noise_test": {
          "ks_statistic": 0.044,
          "p_value": 0.28779764348473313,
          "is_noise_changed": false
        }
      },
      "8": {
        "is_shifted": false,
        "parents": [
          6
        ],
        "function_test": {
          "f_statistic": 1.877843172404848,
          "p_value": 0.17073358467235134,
          "is_function_changed": false,
          "beta_env1": [
            0.048956172127293154
          ],
          "beta_env2": [
            0.11014252486933301
          ]
        },
        "noise_test": {
          "ks_statistic": 0.031,
          "p_value": 0.7228251828701066,
          "is_noise_changed": false
        }
      },
      "9": {
        "is_shifted": false,
        "parents": [
          3
        ],
        "function_test": {
          "f_statistic": 2.3024798202931787,
          "p_value": 0.1293259889753906,
          "is_function_changed": false,
          "beta_env1": [
            0.11677713829869034
          ],
          "beta_env2": [
            0.18386767777144306
          ]
        },
        "noise_test": {
          "ks_statistic": 0.023,
          "p_value": 0.9542189106778983,
          "is_noise_changed": false
        }
      },
      "10": {
        "is_shifted": false,
        "parents": [
          3
        ],
        "function_test": {
          "f_statistic": 0.01438832054270418,
          "p_value": 0.9045337778441749,
          "is_function_changed": false,
          "beta_env1": [
            0.11213933542004136
          ],
          "beta_env2": [
            0.1068414567720768
          ]
        },
        "noise_test": {
          "ks_statistic": 0.035,
          "p_value": 0.5728904395829821,
          "is_noise_changed": false
        }
      },
      "11": {
        "is_shifted": false,
        "parents": [
          3
        ],
        "function_test": {
          "f_statistic": 3.4678124231220586,
          "p_value": 0.06272085686387774,
          "is_function_changed": false,
          "beta_env1": [
            0.10206430428130038
          ],
          "beta_env2": [
            0.1840865337243748
          ]
        },
        "noise_test": {
          "ks_statistic": 0.036,
          "p_value": 0.5362766985932181,
          "is_noise_changed": false
        }
      },
      "12": {
        "is_shifted": true,
        "parents": [
          6
        ],
        "function_test": {
          "f_statistic": 4.200842186012156,
          "p_value": 0.040534342534130685,
          "is_function_changed": true,
          "beta_env1": [
            0.028685173319592076
          ],
          "beta_env2": [
            0.11743314908808958
          ]
        },
        "noise_test": {
          "ks_statistic": 0.025,
          "p_value": 0.9136894237272155,
          "is_noise_changed": false
        }
      },
      "13": {
        "is_shifted": false,
        "parents": [
          9
        ],
        "function_test": {
          "f_statistic": 2.749641111895507,
          "p_value": 0.09743338844112615,
          "is_function_changed": false,
          "beta_env1": [
            0.16103399045693517
          ],
          "beta_env2": [
            0.08850878590965358
          ]
        },
        "noise_test": {
          "ks_statistic": 0.031,
          "p_value": 0.7228251828701066,
          "is_noise_changed": false
        }
      },
      "14": {
        "is_shifted": true,
        "parents": [
          10
        ],
        "function_test": {
          "f_statistic": 3.024633374292364,
          "p_value": 0.08216302196401226,
          "is_function_changed": false,
          "beta_env1": [
            0.1509877996559291
          ],
          "beta_env2": [
            0.05621717672592796
          ]
        },
        "noise_test": {
          "ks_statistic": 0.119,
          "p_value": 1.3787445928064639e-06,
          "is_noise_changed": true
        }
      },
      "15": {
        "is_shifted": true,
        "parents": [
          10
        ],
        "function_test": {
          "f_statistic": 4.995335641398412,
          "p_value": 0.025525966706600123,
          "is_function_changed": true,
          "beta_env1": [
            0.08405701149660266
          ],
          "beta_env2": [
            0.1882587179517049
          ]
        },
        "noise_test": {
          "ks_statistic": 0.079,
          "p_value": 0.0038826726503625613,
          "is_noise_changed": true
        }
      },
      "16": {
        "is_shifted": true,
        "parents": [
          14
        ],
        "function_test": {
          "f_statistic": 16.655132326948497,
          "p_value": 4.6594132411703626e-05,
          "is_function_changed": true,
          "beta_env1": [
            0.1410757657265064
          ],
          "beta_env2": [
            -0.009857717104004349
          ]
        },
        "noise_test": {
          "ks_statistic": 0.038,
          "p_value": 0.4659595288557257,
          "is_noise_changed": false
        }
      },
      "17": {
        "is_shifted": false,
        "parents": [
          3
        ],
        "function_test": {
          "f_statistic": 1.002891988884507,
          "p_value": 0.31673312926719255,
          "is_function_changed": false,
          "beta_env1": [
            0.1073226241641774
          ],
          "beta_env2": [
            0.15196255432398087
          ]
        },
        "noise_test": {
          "ks_statistic": 0.03,
          "p_value": 0.7593695685682871,
          "is_noise_changed": false
        }
      },
      "18": {
        "is_shifted": true,
        "parents": [
          1
        ],
        "function_test": {
          "f_statistic": 5.045893184520103,
          "p_value": 0.024793325317302384,
          "is_function_changed": true,
          "beta_env1": [
            0.18646488997295851
          ],
          "beta_env2": [
            0.08681621802239303
          ]
        },
        "noise_test": {
          "ks_statistic": 0.031,
          "p_value": 0.7228251828701066,
          "is_noise_changed": false
        }
      },
      "19": {
        "is_shifted": true,
        "parents": [
          5
        ],
        "function_test": {
          "f_statistic": 4.988054255184419,
          "p_value": 0.025633322143400417,
          "is_function_changed": true,
          "beta_env1": [
            0.1194359652610735
          ],
          "beta_env2": [
            0.2198967817513927
          ]
        },
        "noise_test": {
          "ks_statistic": 0.075,
          "p_value": 0.007195361443046065,
          "is_noise_changed": true
        }
      },
      "20": {
        "is_shifted": false,
        "parents": [
          4
        ],
        "function_test": {
          "f_statistic": 0.00357934192084785,
          "p_value": 0.9522989311906076,
          "is_function_changed": false,
          "beta_env1": [
            0.17414255741327084
          ],
          "beta_env2": [
            0.1714400977418445
          ]
        },
        "noise_test": {
          "ks_statistic": 0.025,
          "p_value": 0.9136894237272155,
          "is_noise_changed": false
        }
      },
      "21": {
        "is_shifted": false,
        "parents": [
          10
        ],
        "function_test": {
          "f_statistic": 1.540623532897897,
          "p_value": 0.21467086780203026,
          "is_function_changed": false,
          "beta_env1": [
            0.1220794137800514
          ],
          "beta_env2": [
            0.17920322378435058
          ]
        },
        "noise_test": {
          "ks_statistic": 0.047,
          "p_value": 0.21939649929677082,
          "is_noise_changed": false
        }
      },
      "22": {
        "is_shifted": true,
        "parents": [
          12
        ],
        "function_test": {
          "f_statistic": 3.212235707427646,
          "p_value": 0.0732409495519517,
          "is_function_changed": false,
          "beta_env1": [
            0.06331373077936818
          ],
          "beta_env2": [
            -0.03733762490895275
          ]
        },
        "noise_test": {
          "ks_statistic": 0.146,
          "p_value": 1.035413447317725e-09,
          "is_noise_changed": true
        }
      },
      "23": {
        "is_shifted": false,
        "parents": [
          3
        ],
        "function_test": {
          "f_statistic": 3.015901898207746,
          "p_value": 0.08260586099719724,
          "is_function_changed": false,
          "beta_env1": [
            0.18954602592024886
          ],
          "beta_env2": [
            0.11126375003904473
          ]
        },
        "noise_test": {
          "ks_statistic": 0.031,
          "p_value": 0.7228251828701066,
          "is_noise_changed": false
        }
      },
      "24": {
        "is_shifted": false,
        "parents": [
          9
        ],
        "function_test": {
          "f_statistic": 2.3972917497212425,
          "p_value": 0.12170403993354617,
          "is_function_changed": false,
          "beta_env1": [
            0.14926156982786384
          ],
          "beta_env2": [
            0.08405208372019274
          ]
        },
        "noise_test": {
          "ks_statistic": 0.037,
          "p_value": 0.5005673707894058,
          "is_noise_changed": false
        }
      },
      "25": {
        "is_shifted": true,
        "parents": [
          4
        ],
        "function_test": {
          "f_statistic": 0.9818208031365683,
          "p_value": 0.32186979317161757,
          "is_function_changed": false,
          "beta_env1": [
            0.09494062781504174
          ],
          "beta_env2": [
            0.04035589390440181
          ]
        },
        "noise_test": {
          "ks_statistic": 0.119,
          "p_value": 1.3787445928064639e-06,
          "is_noise_changed": true
        }
      },
      "26": {
        "is_shifted": true,
        "parents": [
          6
        ],
        "function_test": {
          "f_statistic": 8.199245982870922,
          "p_value": 0.004234536053176918,
          "is_function_changed": true,
          "beta_env1": [
            0.049006854001469376
          ],
          "beta_env2": [
            0.16984528531823934
          ]
        },
        "noise_test": {
          "ks_statistic": 0.033,
          "p_value": 0.647814872077161,
          "is_noise_changed": false
        }
      },
      "27": {
        "is_shifted": false,
        "parents": [
          9
        ],
        "function_test": {
          "f_statistic": 1.0249249161623666,
          "p_value": 0.3114763512272196,
          "is_function_changed": false,
          "beta_env1": [
            0.13326498539813514
          ],
          "beta_env2": [
            0.08907657513297271
          ]
        },
        "noise_test": {
          "ks_statistic": 0.033,
          "p_value": 0.647814872077161,
          "is_noise_changed": false
        }
      },
      "28": {
        "is_shifted": true,
        "parents": [
          12
        ],
        "function_test": {
          "f_statistic": 8.422542930727172,
          "p_value": 0.003746604100524853,
          "is_function_changed": true,
          "beta_env1": [
            0.056007870734854324
          ],
          "beta_env2": [
            0.19251916952010498
          ]
        },
        "noise_test": {
          "ks_statistic": 0.089,
          "p_value": 0.0007213629171338913,
          "is_noise_changed": true
        }
      },
      "29": {
        "is_shifted": false,
        "parents": [
          5
        ],
        "function_test": {
          "f_statistic": 0.0007652413694099781,
          "p_value": 0.9779337023996246,
          "is_function_changed": false,
          "beta_env1": [
            0.09261069289193173
          ],
          "beta_env2": [
            0.09139937716306133
          ]
        },
        "noise_test": {
          "ks_statistic": 0.025,
          "p_value": 0.9136894237272155,
          "is_noise_changed": false
        }
      },
      "30": {
        "is_shifted": true,
        "parents": [
          0
        ],
        "function_test": {
          "f_statistic": 6.494435564938638,
          "p_value": 0.010895579143285317,
          "is_function_changed": true,
          "beta_env1": [
            -0.04022167805923751
          ],
          "beta_env2": [
            0.03611351627778964
          ]
        },
        "noise_test": {
          "ks_statistic": 0.033,
          "p_value": 0.647814872077161,
          "is_noise_changed": false
        }
      },
      "31": {
        "is_shifted": true,
        "parents": [
          5
        ],
        "function_test": {
          "f_statistic": 4.83997118251357,
          "p_value": 0.02792159389271165,
          "is_function_changed": true,
          "beta_env1": [
            0.07750199836823465
          ],
          "beta_env2": [
            -0.04241238715302772
          ]
        },
        "noise_test": {
          "ks_statistic": 0.118,
          "p_value": 1.7492235820299696e-06,
          "is_noise_changed": true
        }
      },
      "32": {
        "is_shifted": false,
        "parents": [
          3
        ],
        "function_test": {
          "f_statistic": 2.7406273283518248,
          "p_value": 0.09798355546757942,
          "is_function_changed": false,
          "beta_env1": [
            0.12680027861894327
          ],
          "beta_env2": [
            0.19921087474438995
          ]
        },
        "noise_test": {
          "ks_statistic": 0.027,
          "p_value": 0.8595454206943325,
          "is_noise_changed": false
        }
      },
      "33": {
        "is_shifted": false,
        "parents": [
          9
        ],
        "function_test": {
          "f_statistic": 0.19347272442125943,
          "p_value": 0.6600895009117724,
          "is_function_changed": false,
          "beta_env1": [
            0.09555660520455646
          ],
          "beta_env2": [
            0.07629596311800715
          ]
        },
        "noise_test": {
          "ks_statistic": 0.029,
          "p_value": 0.7946637387576738,
          "is_noise_changed": false
        }
      },
      "34": {
        "is_shifted": false,
        "parents": [
          10
        ],
        "function_test": {
          "f_statistic": 0.7592520313894353,
          "p_value": 0.3836674894292894,
          "is_function_changed": false,
          "beta_env1": [
            0.08264638040597191
          ],
          "beta_env2": [
            0.12051659628969667
          ]
        },
        "noise_test": {
          "ks_statistic": 0.033,
          "p_value": 0.647814872077161,
          "is_noise_changed": false
        }
      },
      "35": {
        "is_shifted": false,
        "parents": [
          32
        ],
        "function_test": {
          "f_statistic": 0.5585132708670667,
          "p_value": 0.4549479178721767,
          "is_function_changed": false,
          "beta_env1": [
            0.13070427644506893
          ],
          "beta_env2": [
            0.09743744820428088
          ]
        },
        "noise_test": {
          "ks_statistic": 0.022,
          "p_value": 0.9690010280430694,
          "is_noise_changed": false
        }
      },
      "36": {
        "is_shifted": false,
        "parents": [
          6
        ],
        "function_test": {
          "f_statistic": 2.399731887082433,
          "p_value": 0.12151457852904501,
          "is_function_changed": false,
          "beta_env1": [
            0.07433208304284625
          ],
          "beta_env2": [
            0.14165108024537046
          ]
        },
        "noise_test": {
          "ks_statistic": 0.029,
          "p_value": 0.7946637387576738,
          "is_noise_changed": false
        }
      },
      "37": {
        "is_shifted": false,
        "parents": [
          10
        ],
        "function_test": {
          "f_statistic": 1.583714567015836,
          "p_value": 0.20837362920685165,
          "is_function_changed": false,
          "beta_env1": [
            0.07831704249980027
          ],
          "beta_env2": [
            0.13362737104919317
          ]
        },
        "noise_test": {
          "ks_statistic": 0.034,
          "p_value": 0.6101664688189142,
          "is_noise_changed": false
        }
      },
      "38": {
        "is_shifted": false,
        "parents": [
          3
        ],
        "function_test": {
          "f_statistic": 1.4371508564723225,
          "p_value": 0.23074325613552904,
          "is_function_changed": false,
          "beta_env1": [
            0.16465055236445741
          ],
          "beta_env2": [
            0.11193661858485704
          ]
        },
        "noise_test": {
          "ks_statistic": 0.047,
          "p_value": 0.21939649929677082,
          "is_noise_changed": false
        }
      },
      "39": {
        "is_shifted": false,
        "parents": [
          0
        ],
        "function_test": {
          "f_statistic": 0.2852723721727996,
          "p_value": 0.5933256358425391,
          "is_function_changed": false,
          "beta_env1": [
            -0.0030516023484014393
          ],
          "beta_env2": [
            0.013573832258258822
          ]
        },
        "noise_test": {
          "ks_statistic": 0.034,
          "p_value": 0.6101664688189142,
          "is_noise_changed": false
        }
      }
    },
    "metrics": {
      "true_positives": [
        14,
        15,
        19,
        22,
        25,
        28,
        31
      ],
      "false_positives": [
        12,
        16,
        18,
        26,
        30
      ],
      "false_negatives": [
        21
      ],
      "precision": 0.5833333333333334,
      "recall": 0.875,
      "f1_score": 0.7000000000000001
    }
  },
  "complexity_analysis": {
    "success": true,
    "error": null,
    "dataset_params": {
      "n_samples": 1000,
      "n_nodes": 40,
      "avg_parents": 0.975,
      "max_parents": 1,
      "total_edges": 39
    },
    "time_complexity": {
      "execution_time_seconds": 0.13482165336608887,
      "execution_time_minutes": 0.0022470275561014812
    },
    "space_complexity": {
      "peak_rss_mb": 590.45703125,
      "peak_memory_increase_mb": 0.0,
      "start_rss_mb": 590.45703125,
      "os": "Linux"
    },
    "scalability_metrics": {
      "time_per_node_sec": 0.003370541334152222,
      "time_per_sample_sec": 0.00013482165336608885,
      "time_per_edge_sec": 0.0034569654709253558,
      "memory_per_node_mb": 0.0,
      "memory_per_sample_mb": 0.0
    }
  }
}